{
  "stocks": [
    {
      "name": "AAPL（苹果）",
      "market": "US",
      "symbol": "AAPL.US",
      "stock_type": "cyclical",
      "sector": "tech"
    },
    {
      "name": "MSFT（微软）",
      "market": "US",
      "symbol": "MSFT.US",
      "stock_type": "cyclical",
      "sector": "tech"
    },
    {
      "name": "00700（腾讯）",
      "market": "HK",
      "symbol": "700.HK",
      "stock_type": "cyclical",
      "sector": "internet"
    },
    {
      "name": "09988（阿里巴巴）",
      "market": "HK",
      "symbol": "9988.HK",
      "stock_type": "cyclical",
      "sector": "internet"
    },
    {
      "name": "600519（贵州茅台）",
      "market": "CN",
      "symbol": "600519.SH",
      "stock_type": "cyclical",
      "sector": "consumer"
    },
    {
      "name": "300750（宁德时代）",
      "market": "CN",
      "symbol": "300750.SZ",
      "stock_type": "cyclical",
      "sector": "new_energy"
    }
  ]
}
